cs_framework/__init__.py
cs_framework/cli.py
cs_framework/core/__init__.py
cs_framework/core/agent.py
cs_framework/core/concept.py
cs_framework/core/event.py
cs_framework/core/event_bridge.py
cs_framework/core/invariant.py
cs_framework/core/llm.py
cs_framework/core/synchronization.py
cs_framework/core/transport.py
cs_framework/core/yaml_loader.py
cs_framework/engine/__init__.py
cs_framework/engine/runner.py
cs_framework/engine/scenario.py
cs_framework/engine/shadow_runner.py
cs_framework/logging/__init__.py
cs_framework/logging/logger.py
cs_framework/logging/ontology.py
cs_framework/skills/architect/SKILL.md
cs_framework/skills/debugger/SKILL.md
cs_framework/skills/dev/SKILL.md
cs_framework/skills/fuzzer/SKILL.md
cs_framework/skills/linter/SKILL.md
cs_framework/tools/architect.py
cs_framework/tools/debugger.py
cs_framework/tools/linter.py
cs_framework/tools/scenario_runner.py
cs_framework/tools/speckit_integration/__init__.py
cs_framework/tools/speckit_integration/integration.py
cs_framework/tools/speckit_integration/templates/csfw_constitution.md
cs_framework/tools/speckit_integration/templates/csfw_plan_section.md
cs_framework/tools/speckit_integration/templates/csfw_task_note.md
cs_gui/__init__.py
cs_gui/graph_loader.py
cs_gui/main.py
examples/agent_demo/main.py
examples/distributed_demo/main.py
examples/pacman/play.py
examples/pacman/run.py
examples/pacman/src/concepts/board.py
examples/pacman/src/concepts/gameloop.py
examples/pacman/src/concepts/ghost.py
examples/pacman/src/concepts/inputsystem.py
examples/pacman/src/concepts/pacman.py
examples/roguelike/hybrid_control.py
examples/roguelike/main.py
examples/roguelike/run.py
examples/roguelike/view_scene.py
examples/roguelike/virtual_input.py
examples/roguelike/src/concepts/dungeon.py
examples/roguelike/src/concepts/gamestate.py
examples/roguelike/src/concepts/item.py
examples/roguelike/src/concepts/monster.py
examples/roguelike/src/concepts/player.py
examples/shadow_demo/main.py
cs_framework-0.1.6.dist-info/METADATA
cs_framework-0.1.6.dist-info/WHEEL
cs_framework-0.1.6.dist-info/entry_points.txt
cs_framework-0.1.6.dist-info/top_level.txt
cs_framework-0.1.6.dist-info/RECORD
