Metadata-Version: 2.4
Name: cs-framework
Version: 0.1.6
Summary: A Python framework implementing the Concept-Synchronization Constitution
Author-email: shuntacurosu <shuntacurosu@users.noreply.github.com>
License: MIT
Project-URL: Homepage, https://github.com/shuntacurosu/cs-framework
Project-URL: Repository, https://github.com/shuntacurosu/cs-framework
Project-URL: Issues, https://github.com/shuntacurosu/cs-framework/issues
Requires-Python: >=3.10
Requires-Dist: rdflib>=7.0.0
Requires-Dist: pyyaml>=6.0
Requires-Dist: loguru>=0.7.0
Requires-Dist: networkx>=3.0
Requires-Dist: pydantic>=2.0.0
Provides-Extra: visualization
Requires-Dist: nicegui>=1.4.0; extra == "visualization"
Provides-Extra: dev
Requires-Dist: pytest>=7.0.0; extra == "dev"
